yeswecansvg/__init__.py
yeswecansvg/yeswecansvg.py
yeswecansvg-0.1.0.dist-info/DESCRIPTION.rst
yeswecansvg-0.1.0.dist-info/METADATA
yeswecansvg-0.1.0.dist-info/RECORD
yeswecansvg-0.1.0.dist-info/WHEEL
yeswecansvg-0.1.0.dist-info/entry_points.txt
yeswecansvg-0.1.0.dist-info/metadata.json
yeswecansvg-0.1.0.dist-info/top_level.txt
