Metadata-Version: 2.0
Name: yeswecansvg
Version: 0.1.0
Summary: Clean your SVGs so Illustrator won't tell you it CANT.
Home-page: http://github.com/emamd/yeswecansvg
Author: Armand Emamdjomeh
Author-email: armand.emamdjomeh@washpost.com
License: MIT
Download-URL: http://github.com/emamd/yeswecansvg.git
Platform: UNKNOWN
Classifier: Programming Language :: Python
Classifier: Programming Language :: Python :: 2.7
Classifier: Programming Language :: Python :: 3.3
Classifier: Programming Language :: Python :: 3.4
